async_extensions/__init__.py
async_extensions/blocking.py
async_extensions/cancellation.py
async_extensions/channels.py
async_extensions/collecting.py
async_extensions/completion.py
async_extensions/current.py
async_extensions/defaults.py
async_extensions/errors.py
async_extensions/files.py
async_extensions/from_thread.py
async_extensions/low_level.py
async_extensions/paths.py
async_extensions/processes.py
async_extensions/py.typed
async_extensions/resources.py
async_extensions/results.py
async_extensions/runners.py
async_extensions/signals.py
async_extensions/sleeping.py
async_extensions/standard.py
async_extensions/synchronization.py
async_extensions/tagged.py
async_extensions/task_groups.py
async_extensions/task_statuses.py
async_extensions/types.py
async_extensions/waiting.py
async_extensions-3.1.2.dist-info/LICENSE
async_extensions-3.1.2.dist-info/METADATA
async_extensions-3.1.2.dist-info/WHEEL
async_extensions-3.1.2.dist-info/RECORD
