Metadata-Version: 2.1
Name: async-extensions
Version: 3.1.2
Summary: Asynchronous extensions.
Home-page: https://github.com/nekitdev/async-extensions
License: MIT
Keywords: python,async,extensions
Author: nekitdev
Requires-Python: >=3.8
Classifier: Development Status :: 5 - Production/Stable
Classifier: Intended Audience :: Developers
Classifier: License :: OSI Approved :: MIT License
Classifier: Operating System :: OS Independent
Classifier: Programming Language :: Python :: 3
Classifier: Programming Language :: Python :: 3.8
Classifier: Programming Language :: Python :: 3.9
Classifier: Programming Language :: Python :: 3.10
Classifier: Programming Language :: Python :: 3.11
Classifier: Programming Language :: Python :: 3.12
Classifier: Topic :: Utilities
Classifier: Typing :: Typed
Requires-Dist: anyio (>=4.3.0)
Requires-Dist: attrs (>=23.2.0)
Requires-Dist: funcs (>=0.9.2)
Requires-Dist: named (>=1.4.2)
Requires-Dist: sniffio (>=1.3.1)
Requires-Dist: solus (>=1.2.2)
Requires-Dist: typing-aliases (>=1.10.0)
Requires-Dist: typing-extensions (>=4.10.0)
Requires-Dist: wraps (>=0.9.2)
Project-URL: Chat, https://nekit.dev/chat
Project-URL: Funding, https://nekit.dev/funding
Project-URL: Issues, https://github.com/nekitdev/async-extensions/issues
Project-URL: Repository, https://github.com/nekitdev/async-extensions
